X14TianXuehuiAnzhuoKaifa/README.md
X14TianXuehuiAnzhuoKaifa/__init__.py
X14TianXuehuiAnzhuoKaifa/__main__.py
X14TianXuehuiAnzhuoKaifa/file.epub
X14TianXuehuiAnzhuoKaifa/index.html
X14TianXuehuiAnzhuoKaifa/css/__init__.py
X14TianXuehuiAnzhuoKaifa/css/annotations.css
X14TianXuehuiAnzhuoKaifa/css/main.css
X14TianXuehuiAnzhuoKaifa/css/normalize.css
X14TianXuehuiAnzhuoKaifa/css/popup.css
X14TianXuehuiAnzhuoKaifa/font/__init__.py
X14TianXuehuiAnzhuoKaifa/font/fontello.eot
X14TianXuehuiAnzhuoKaifa/font/fontello.svg
X14TianXuehuiAnzhuoKaifa/font/fontello.ttf
X14TianXuehuiAnzhuoKaifa/font/fontello.woff
X14TianXuehuiAnzhuoKaifa/img/__init__.py
X14TianXuehuiAnzhuoKaifa/img/annotator-glyph-sprite.png
X14TianXuehuiAnzhuoKaifa/img/annotator-icon-sprite.png
X14TianXuehuiAnzhuoKaifa/img/apple-touch-icon.png
X14TianXuehuiAnzhuoKaifa/img/cancelfullscreen.png
X14TianXuehuiAnzhuoKaifa/img/close.png
X14TianXuehuiAnzhuoKaifa/img/fullscreen.png
X14TianXuehuiAnzhuoKaifa/img/loader.gif
X14TianXuehuiAnzhuoKaifa/img/menu-icon.png
X14TianXuehuiAnzhuoKaifa/img/save.png
X14TianXuehuiAnzhuoKaifa/img/saved.png
X14TianXuehuiAnzhuoKaifa/img/settings-s.png
X14TianXuehuiAnzhuoKaifa/img/settings.png
X14TianXuehuiAnzhuoKaifa/img/star.png
X14TianXuehuiAnzhuoKaifa/js/__init__.py
X14TianXuehuiAnzhuoKaifa/js/epub.js
X14TianXuehuiAnzhuoKaifa/js/epub.min.js
X14TianXuehuiAnzhuoKaifa/js/epub.min.map
X14TianXuehuiAnzhuoKaifa/js/hooks.min.js
X14TianXuehuiAnzhuoKaifa/js/hooks.min.map
X14TianXuehuiAnzhuoKaifa/js/reader.js
X14TianXuehuiAnzhuoKaifa/js/reader.js.map
X14TianXuehuiAnzhuoKaifa/js/reader.min.js
X14TianXuehuiAnzhuoKaifa/js/reader.min.map
X14TianXuehuiAnzhuoKaifa/js/hooks/__init__.py
X14TianXuehuiAnzhuoKaifa/js/hooks/extensions/__init__.py
X14TianXuehuiAnzhuoKaifa/js/hooks/extensions/highlight.js
X14TianXuehuiAnzhuoKaifa/js/libs/__init__.py
X14TianXuehuiAnzhuoKaifa/js/libs/jquery.min.js
X14TianXuehuiAnzhuoKaifa/js/libs/localforage.min.js
X14TianXuehuiAnzhuoKaifa/js/libs/screenfull.js
x14_tian_xuehui_anzhuo_kaifa-2024.2.29.0.dist-info/METADATA
x14_tian_xuehui_anzhuo_kaifa-2024.2.29.0.dist-info/WHEEL
x14_tian_xuehui_anzhuo_kaifa-2024.2.29.0.dist-info/entry_points.txt
x14_tian_xuehui_anzhuo_kaifa-2024.2.29.0.dist-info/top_level.txt
x14_tian_xuehui_anzhuo_kaifa-2024.2.29.0.dist-info/RECORD
